axiom_py/__init__.py
axiom_py/annotations.py
axiom_py/client.py
axiom_py/datasets.py
axiom_py/logging.py
axiom_py/structlog.py
axiom_py/tokens.py
axiom_py/users.py
axiom_py/util.py
axiom_py/version.py
axiom_py/query/__init__.py
axiom_py/query/aggregation.py
axiom_py/query/filter.py
axiom_py/query/options.py
axiom_py/query/query.py
axiom_py/query/result.py
axiom_py-0.9.0.dist-info/METADATA
axiom_py-0.9.0.dist-info/WHEEL
axiom_py-0.9.0.dist-info/licenses/LICENSE
axiom_py-0.9.0.dist-info/RECORD
