Metadata-Version: 2.4
Name: axiom-py
Version: 0.9.0
Summary: Official bindings for the Axiom API
Project-URL: Homepage, https://axiom.co
Project-URL: Repository, https://github.com/axiomhq/axiom-py.git
Project-URL: Issues, https://github.com/axiomhq/axiom-py/issues
License: MIT License
License-File: LICENSE
Classifier: Development Status :: 4 - Beta
Classifier: Intended Audience :: Developers
Classifier: License :: OSI Approved :: MIT License
Classifier: Programming Language :: Python :: 3.8
Classifier: Programming Language :: Python :: 3.9
Classifier: Programming Language :: Python :: 3.10
Classifier: Programming Language :: Python :: 3.11
Classifier: Programming Language :: Python :: 3.12
Classifier: Topic :: System :: Logging
Requires-Python: >=3.8
Requires-Dist: dacite>=1.8.1
Requires-Dist: iso8601>=1.0.2
Requires-Dist: ndjson>=0.3.1
Requires-Dist: pyhumps>=3.8.0
Requires-Dist: requests-toolbelt>=1.0.0
Requires-Dist: requests>=2.32.3
Requires-Dist: ujson>=5.10.0
